LICENSE.txt
MANIFEST.in
README.rst
setup.py
amonpy/__init__.py
amonpy/config.py
amonpy/exceptions.py
amonpy/sender.py
amonpy/tests.py
amonpy.egg-info/PKG-INFO
amonpy.egg-info/SOURCES.txt
amonpy.egg-info/dependency_links.txt
amonpy.egg-info/not-zip-safe
amonpy.egg-info/requires.txt
amonpy.egg-info/top_level.txt
amonpy/adapters/__init__.py
amonpy/adapters/django_.py
amonpy/protocols/__init__.py
amonpy/protocols/http.py
amonpy/protocols/zeromq.py