Metadata-Version: 1.1
Name: amonpy
Version: 0.4.4
Summary: Python client for the Amon API
Home-page: https://github.com/martinrusev/amonpy
Author: Martin Rusev
Author-email: martin@amon.cx
License: BSD
Keywords: amon,monitoring,logging,exception logging
Platform: UNKNOWN
Classifier: Programming Language :: Python
Classifier: Topic :: Software Development :: Libraries :: Python Modules
Classifier: Environment :: Web Environment
